README.rst
setup.py
flask_db_tools/__init__.py
flask_db_tools/sqllite_db.py
flask_db_tools.egg-info/PKG-INFO
flask_db_tools.egg-info/SOURCES.txt
flask_db_tools.egg-info/dependency_links.txt
flask_db_tools.egg-info/requires.txt
flask_db_tools.egg-info/top_level.txt